casttube/YouTubeSession.py
casttube/__init__.py
casttube-0.2.1.data/data/LICENSE
casttube-0.2.1.dist-info/LICENSE
casttube-0.2.1.dist-info/METADATA
casttube-0.2.1.dist-info/WHEEL
casttube-0.2.1.dist-info/top_level.txt
casttube-0.2.1.dist-info/RECORD
