Metadata-Version: 2.1
Name: casttube
Version: 0.2.1
Summary: YouTube chromecast api
Home-page: http://github.com/ur1katz/casttube
Author: Uri Katz
Author-email: 4urikatz@gmail.com
License: MIT
Keywords: youtube,chromecast,youtube-api
Platform: UNKNOWN
